{
  "design_products": [
    {
      "id": 1,
      "name": "Скандинавский увлажняющий крем",
      "category": "Уход за лицом",
      "price": 5222,
      "material": "Гиалуроновая кислота, натуральные масла",
      "description": "Минималистичный крем с легкой текстурой",
      "photo_url": "https://lola.by/image/cache/tov/big/390.jpg",
      "style": "Скандинавский",
      "in_stock": true,
      "favorites": false,
      "cart": false
    },
    {
      "id": 2,
      "name": "Омолаживающая сыворотка Eames",
      "category": "Сыворотки",
      "price": 26214,
      "material": "Ретинол, пептиды",
      "description": "Премиальная антивозрастная сыворотка",
      "photo_url": "https://milfey-shop.ru/image/cache/catalog/image-skincare/omolazivausaa-syvorotka-so-stvolovymi-kletkami_1-640x640_jpg.webp",
      "style": "Люкс",
      "in_stock": true,
      "favorites": false,
      "cart": false
    },
    {
      "id": 3,
      "name": "Гелевая маска для лица",
      "category": "Маски",
      "price": 3964,
      "material": "Алоэ вера, экстракт зеленого чая",
      "description": "Успокаивающая и увлажняющая маска",
      "photo_url": "https://milan.by/assets/images/products/9877/est0002.jpg",
      "style": "Натуральный",
      "in_stock": false,
      "favorites": false,
      "cart": false
    },
    {
      "id": 4,
      "name": "LED-маска для лица Artemide",
      "category": "Гаджеты",
      "price": 6795,
      "material": "Пластик, LED-лампы",
      "description": "Домашний прибор для светотерапии",
      "photo_url": "https://basket-11.wbbasket.ru/vol1604/part160425/160425870/images/big/1.webp",
      "style": "Современный",
      "in_stock": true,
      "favorites": false,
      "cart": false
    },
    {
      "id": 5,
      "name": "Роликовый массажер для лица",
      "category": "Аксессуары",
      "price": 14219,
      "material": "Камень гуаша, сталь",
      "description": "Инструмент для лимфодренажного массажа",
      "photo_url": "https://ltbeauty.by/wa-data/public/shop/products/86/00/86/images/306/306.970.jpg",
      "style": "Восточный",
      "in_stock": false,
      "favorites": false,
      "cart": false
    },
    {
      "id": 6,
      "name": "Зеркало с увеличением для макияжа",
      "category": "Аксессуары",
      "price": 8913,
      "material": "Зеркало, пластик",
      "description": "Профессиональное зеркало с подсветкой",
      "photo_url": "https://basket-01.wbbasket.ru/vol102/part10213/10213311/images/big/1.webp",
      "style": "Профессиональный",
      "in_stock": true,
      "favorites": false,
      "cart": false
    },
    {
      "id": 7,
      "name": "Набор для ухода за кожей Noguchi",
      "category": "Наборы",
      "price": 18811,
      "material": "Натуральные компоненты",
      "description": "Полный комплект для ежедневного ухода",
      "photo_url": "https://36best.com/upload/iblock/f69/84ia2cwgsycehlaz0cl7ndtle905awc2.jpg",
      "style": "Премиум",
      "in_stock": false,
      "favorites": false,
      "cart": false
    },
    {
      "id": 8,
      "name": "Керамическая емкость для хранения",
      "category": "Аксессуары",
      "price": 2622,
      "material": "Керамика",
      "description": "Стильный контейнер для косметики",
      "photo_url": "https://ir-3.ozone.ru/s3/multimedia-1-b/w500/7072861655.jpg",
      "style": "Минимализм",
      "in_stock": false,
      "favorites": false,
      "cart": false
    },
    {
      "id": 9,
      "name": "Набор для СПА-процедур Barcelona",
      "category": "Наборы",
      "price": 50000,
      "material": "Натуральные компоненты",
      "description": "Профессиональный набор для домашнего ухода",
      "photo_url": "https://basket-16.wbbasket.ru/vol2556/part255600/255600806/images/c516x688/1.webp",
      "style": "Люкс",
      "in_stock": false,
      "favorites": false,
      "cart": false
    },
    {
      "id": 10,
      "name": "Ультразвуковой очиститель кожи",
      "category": "Гаджеты",
      "price": 6018,
      "material": "Пластик, металл",
      "description": "Прибор для глубокого очищения пор",
      "photo_url": "https://kitfort.ru/upload/resize_cache/webp/upload/iblock/fd5/sm12r97fz2n92pwpycuqfpn3k56utqi7.webp",
      "style": "Современный",
      "in_stock": true,
      "favorites": false,
      "cart": false
    },
    {
      "id": 11,
      "name": "Патчи для глаз с золотом",
      "category": "Патчи",
      "price": 2334,
      "material": "Гидрогель, золото",
      "description": "Экспресс-уход для области вокруг глаз",
      "photo_url": "https://korealab.by/image/cache/catalog/PETITFEE/Patchi/gidrogelevye_patchi_dlja_glaz_s_zolotom_i_ulitochnym_mucinom_petitfee_kupit_v_minske_magazin_korealab-800x800.jpg",
      "style": "Люкс",
      "in_stock": false,
      "favorites": false,
      "cart": false
    },
    {
      "id": 12,
      "name": "Микротоковый массажер PH5",
      "category": "Гаджеты",
      "price": 11198,
      "material": "Металл, пластик",
      "description": "Прибор для лифтинга и тонизирования",
      "photo_url": "https://ir-3.ozone.ru/s3/multimedia-1-s/c400/7210606060.jpg",
      "style": "Профессиональный",
      "in_stock": true,
      "favorites": false,
      "cart": false
    },
    {
      "id": 13,
      "name": "Набор масел для лица",
      "category": "Наборы",
      "price": 15121,
      "material": "Натуральные масла",
      "description": "Комплекс масел для разных типов кожи",
      "photo_url": "https://ir-3.ozone.ru/s3/multimedia-o/c1000/6065672520.jpg",
      "style": "Натуральный",
      "in_stock": true,
      "favorites": false,
      "cart": false
    },
    {
      "id": 14,
      "name": "Органайзер для косметики",
      "category": "Аксессуары",
      "price": 4090,
      "material": "Акрил",
      "description": "Система хранения косметических средств",
      "photo_url": "https://www.telemagazin.by/wp-content/uploads/2023/06/organajzer-dlya-kosmetiki_03.jpg",
      "style": "Минимализм",
      "in_stock": true,
      "favorites": false,
      "cart": false
    },
    {
      "id": 15,
      "name": "Пудра с SPF защитой",
      "category": "Макияж",
      "price": 1405,
      "material": "Минеральные компоненты",
      "description": "Защита и матирование в одном продукте",
      "photo_url": "https://encrypted-tbn0.gstatic.com/images?q=tbn:ANd9GcSCxrWcPH05t747JlO9AgIWrJryaCOh4nXlrQ&s",
      "style": "Натуральный",
      "in_stock": false,
      "favorites": false,
      "cart": false
    },
    {
      "id": 16,
      "name": "Спрей для лица с термальной водой",
      "category": "Тонизирующие средства",
      "price": 8745,
      "material": "Термальная вода",
      "description": "Освежающий спрей для мгновенного увлажнения",
      "photo_url": "https://belita.by/upload/iblock/980/75afnu13ota2ujyjttbv7eic2j7g1yw4.jpg",
      "style": "Натуральный",
      "in_stock": true,
      "favorites": false,
      "cart": false
    },
    {
      "id": 17,
      "name": "Дорожный набор для ухода",
      "category": "Наборы",
      "price": 35480,
      "material": "Различные компоненты",
      "description": "Компактный набор для путешествий",
      "photo_url": "https://basket-11.wbbasket.ru/vol1639/part163959/163959071/images/big/1.webp",
      "style": "Дорожный",
      "in_stock": true,
      "favorites": false,
      "cart": false
    },
    {
      "id": 19,
      "name": "Ролик для лица с нефритом",
      "category": "Аксессуары",
      "price": 12500,
      "material": "Нефрит",
      "description": "Массажный инструмент для улучшения микроциркуляции",
      "photo_url": "https://www.beauty-shop.ru/upload/resize_cache/iblock/2b7/512_470_1821712164bebe8964a3cb4f91f48bb72/1301277_5.jpg",
      "style": "Восточный",
      "in_stock": true,
      "favorites": false,
      "cart": false
    },
    {
      "id": 20,
      "name": "Набор для контурной пластики Tulip",
      "category": "Наборы",
      "price": 28990,
      "material": "Гиалуроновая кислота, пептиды",
      "description": "Профессиональный набор для лифтинга",
      "photo_url": "https://static.insales-cdn.com/r/wHidDwXI4pI/rs:fit:500:0:1/q:100/plain/images/products/1/5515/567489931/TCK-003e_1.png@png",
      "style": "Профессиональный",
      "in_stock": true,
      "favorites": false,
      "cart": false
    },
    {
      "id": 21,
      "name": "Патчи для губ Velvet",
      "category": "Патчи",
      "price": 3200,
      "material": "Гидрогель",
      "description": "Интенсивное увлажнение для губ",
      "photo_url": "https://api.apteka.md/media/1798766/conversions/53375-full.jpg",
      "style": "Интенсивный уход",
      "in_stock": true,
      "favorites": false,
      "cart": false
    },
    {
      "id": 22,
      "name": "Карта кожи лица",
      "category": "Аксессуары",
      "price": 6890,
      "material": "Пластик",
      "description": "Схема для анализа состояния кожи",
      "photo_url": "https://burninghut.ru/wp-content/uploads/2021/09/1-5-1.jpg",
      "style": "Профессиональный",
      "in_stock": true,
      "favorites": false,
      "cart": false
    },
    {
      "id": 23,
      "name": "Лампа для лечения акне Arco",
      "category": "Гаджеты",
      "price": 42300,
      "material": "Пластик, LED-лампы",
      "description": "Профессиональный прибор для лечения проблемной кожи",
      "photo_url": "https://ae04.alicdn.com/kf/Hc3716c47cb524b5f818ae62baee121f0L.jpg",
      "style": "Медицинский",
      "in_stock": false,
      "favorites": false,
      "cart": false
    },
    {
      "id": 24,
      "name": "Органайзер для косметики Billy",
      "category": "Аксессуары",
      "price": 12990,
      "material": "Акрил, металл",
      "description": "Вместительная система хранения",
      "photo_url": "https://images.deal.by/59181142_organajzer-dlya-kosmetiki.jpg",
      "style": "Минимализм",
      "in_stock": true,
      "favorites": false,
      "cart": false
    },
    {
      "id": 25,
      "name": "Льняные полотенца для лица",
      "category": "Аксессуары",
      "price": 7450,
      "material": "Лен",
      "description": "Натуральные полотенца для деликатного ухода",
      "photo_url": "https://m.luxury-textile.ru/icache/img.spim.ru/i/tile_trim/1_1/spim.ru/imgup/58168_1528982118.jpg",
      "style": "Эко",
      "in_stock": true,
      "favorites": false,
      "cart": false
    },
    {
      "id": 26,
      "name": "Массажер для лица Panthella",
      "category": "Аксессуары",
      "price": 18700,
      "material": "Пластик, металл",
      "description": "Стильный массажер для улучшения тонуса кожи",
      "photo_url": "https://storage.yandexcloud.net/mostro-gm-media/51edb1c3-ce0e-91eb-3118-5d3ebd471652/6RM9EKT.jpg",
      "style": "Дизайнерский",
      "in_stock": true,
      "favorites": false,
      "cart": false
    },
    {
      "id": 27,
      "name": "Набор для пилинга Extendable",
      "category": "Наборы",
      "price": 45600,
      "material": "Кислоты, ферменты",
      "description": "Профессиональный набор для домашнего пилинга",
      "photo_url": "https://prokeratin.by/upload/iblock/a29/yq83hug4hi4fhinz4fl9kw1rh53m896o/Nabor_dlya_pilinga_kozhi_golovy_Tashe_Professional_Scalp_Care_100_100_ml_.jpg",
      "style": "Профессиональный",
      "in_stock": false,
      "favorites": false,
      "cart": false
    },
    {
      "id": 28,
      "name": "Зеркало с подсветкой для макияжа",
      "category": "Аксессуары",
      "price": 11200,
      "material": "Зеркало, пластик",
      "description": "Профессиональное зеркало с регулируемой подсветкой",
      "photo_url": "https://podaro4ek.by/images/stories/virtuemart/product/zerkalo-s-podsvetkoj-dlya-makiyazha-beloe.webp",
      "style": "Профессиональный",
      "in_stock": true,
      "favorites": false,
      "cart": false
    },
    {
      "id": 29,
      "name": "Маска для лица Snoopy",
      "category": "Маски",
      "price": 9800,
      "material": "Биоцеллюлоза",
      "description": "Интенсивно увлажняющая маска",
      "photo_url": "https://encrypted-tbn0.gstatic.com/images?q=tbn:ANd9GcTi3JFNWiRCbho5sLeM3jED_lG2nxD1KFDV9g&s",
      "style": "Интенсивный уход",
      "in_stock": true,
      "favorites": false,
      "cart": false
    },
    {
      "id": 30,
      "name": "Набор для ухода за кожей",
      "category": "Наборы",
      "price": 23450,
      "material": "Различные компоненты",
      "description": "Полный комплект для ежедневного ухода",
      "photo_url": "https://remontkozji.by/wp-content/uploads/%D1%84%D0%BE%D1%82%D0%BE-%D0%9C%D0%B0%D0%BB%D1%8B%D0%B9-%D0%BD%D0%B0%D0%B1%D0%BE%D1%80-%D0%9B%D0%B5%D0%A2%D1%8D%D0%BA-2.png",
      "style": "Премиум",
      "in_stock": true,
      "favorites": false,
      "cart": false
    }
  ],
  "users": [
    {
      "firstName": "sdfg",
      "lastName": "asdf",
      "middleName": "fsasd",
      "birthDate": "1999-02-23",
      "phone": "+375254242456",
      "email": "gonmoondark@gmail.com",
      "nickname": "sdfasd753",
      "password": "8mcoaFSk@GEc",
      "role": "user",
      "id": 1,
      "cart": [],
      "favorites": []
    },
    {
      "firstName": "рол",
      "lastName": "рол",
      "middleName": "ыва",
      "birthDate": "2000-01-01",
      "phone": "+375254242456",
      "email": "gonmoondark@gmail.com",
      "nickname": "dev",
      "password": "Dk&Je17iSQZv",
      "role": "user",
      "id": 2,
      "cart": [],
      "favorites": []
    },
    {
      "firstName": "admin",
      "lastName": "admin",
      "middleName": "admin",
      "birthDate": "1555-02-23",
      "phone": "+375254242456",
      "email": "gonmoondark@gmail.com",
      "nickname": "admin",
      "password": "admin1",
      "role": "admin",
      "id": 3,
      "cart": [],
      "favorites": []
    }
  ],
  "orders": [
    {
      "564_dev": [
        {
          "id": "1"
        },
        {
          "id": "2"
        }
      ],
      "id": 1
    },
    {
      "564_dev": [
        {
          "id": "1"
        }
      ],
      "id": 2
    },
    {
      "564_dev": [
        {
          "id": "2"
        },
        {
          "id": "3"
        }
      ],
      "id": 3
    },
    {
      "564_dev": [
        {
          "id": "4"
        },
        {
          "id": "3"
        }
      ],
      "id": 4
    },
    {
      "sdfasd753": [
        {
          "id": "8"
        }
      ],
      "id": 5
    },
    {
      "564_dev": [
        {
          "id": "9"
        }
      ],
      "id": 6
    },
    {
      "admin": [
        {
          "id": "1"
        }
      ],
      "id": 7
    },
    {
      "admin": [
        {
          "id": "2"
        }
      ],
      "id": 8
    }
  ],
  "feedback": [
    {
      "nickname": "564_dev",
      "564_dev": [
        "Настольная лампа Artemide — отзыв"
      ],
      "id": 1
    },
    {
      "nickname": "sdfasd753",
      "sdfasd753": [
        "Керамическая ваза — dfs"
      ],
      "id": 2
    },
    {
      "nickname": "admin",
      "admin": [],
      "id": 3
    }
  ]
}